oxli/functions.py
oxli/__init__.py
oxli/build_graph.py
oxli/partition.py
khmer-2.1.1.dist-info/top_level.txt
khmer-2.1.1.dist-info/METADATA
khmer-2.1.1.dist-info/RECORD
khmer-2.1.1.dist-info/WHEEL
khmer/_cpy_hashgraph.hh
khmer/trimming.py
khmer/_cpy_smallcountgraph.hh
khmer/khmer_logger.py
khmer/_khmer.cc
khmer/__init__.py
khmer/_cpy_smallcounttable.hh
khmer/_version.py
khmer/khmer_args.py
khmer/thread_utils.py
khmer/_khmer.so
khmer/utils.py
khmer/_cpy_nodetable.hh
khmer/_cpy_counttable.hh
khmer/kfile.py
khmer/tests/test_read_parsers.py
khmer/tests/test_streaming_io.py
khmer/tests/test_counting_single.py
khmer/tests/test_filter_abund.py
khmer/tests/test_countgraph.py
khmer/tests/test_graph.py
khmer/tests/test_hll.py
khmer/tests/test_assembly.py
khmer/tests/test_nibblestorage.py
khmer/tests/__init__.py
khmer/tests/test_labelhash.py
khmer/tests/khmer_tst_utils.py
khmer/tests/test_cpython_hierarchy.py
khmer/tests/.gitignore
khmer/tests/test_subset_graph.py
khmer/tests/test_script_arguments.py
khmer/tests/test_normalize_by_median.py
khmer/tests/test_script_output.py
khmer/tests/test_oxli_functions.py
khmer/tests/test_hashset.py
khmer/tests/test_nodegraph.py
khmer/tests/test_version.py
khmer/tests/test_sandbox_scripts.py
khmer/tests/test_scripts.py
khmer/tests/test_threaded_sequence_processor.py
khmer/tests/test_functions.py
khmer/tests/test_sequence_validation.py
khmer/tests/test_read_handling.py
khmer/tests/test_read_aligner.py
khmer/tests/test_tabletype.py
khmer/tests/test_lump.py
khmer/tests/test_counttable.py
khmer/tests/test-data/test-overlap1.fa
khmer/tests/test-data/random-20-a.fa
khmer/tests/test-data/100-reads.fq.truncated.bz2
khmer/tests/test-data/100-reads.fq.truncated.gz
khmer/tests/test-data/test-abund-read-paired.fq
khmer/tests/test-data/test-reads.fa
khmer/tests/test-data/paired.malformat.fq
khmer/tests/test-data/paired-mixed.fa
khmer/tests/test-data/goodversion-k32.stoptags
khmer/tests/test-data/test-fastq-reads.fq
khmer/tests/test-data/paired-slash1.fq.1
khmer/tests/test-data/badversion-k32.stoptags
