Metadata-Version: 2.1
Name: khmer
Version: 2.1.1
Summary: khmer k-mer counting library
Home-page: https://khmer.readthedocs.io/
Author: Daniel Standage, Adam Caldwell, Adina Howe, Aditi Gupta, Alex Hyer, Alexander Johan Nederbragt, Ali Aliyari, Amanda Charbonneau, Andreas Härpfer, Bede Constantinides, Benjamin Taylor, Brian Wyss, Cait Sydney, Camille Scott, Charles Pepe-Ranney, Connor T. Skennerton, David Lin, Elmar Bucher, Eric McDonald, Erich Schwarz, Greg Edvenson, Heather L. Wiencko, Humberto Ortiz-Zuazaga, Hussien F. Alameldin, Iván González, Jacob Fenton, James A. Stapleton, James Spencer, Jared Simpson, Jason Pell
Author-email: khmer-project@idyll.org
License: UNKNOWN
Platform: UNKNOWN
Classifier: Environment :: Console
Classifier: Environment :: MacOS X
Classifier: Intended Audience :: Science/Research
Classifier: License :: OSI Approved :: BSD License
Classifier: Natural Language :: English
Classifier: Operating System :: POSIX :: Linux
Classifier: Operating System :: MacOS :: MacOS X
Classifier: Programming Language :: C++
Classifier: Programming Language :: Python :: 2.7
Classifier: Programming Language :: Python :: 3.4
Classifier: Programming Language :: Python :: 3.5
Classifier: Topic :: Scientific/Engineering :: Bio-Informatics
Classifier: Development Status :: 5 - Production/Stable
Provides-Extra: read_aligner_training
Provides-Extra: docs
Provides-Extra: tests
Requires-Dist: screed (>=1.0)
Requires-Dist: bz2file
Requires-Dist: argparse (>=1.2.1); python_version=="2.6"
Provides-Extra: docs
Requires-Dist: sphinx; extra == 'docs'
Requires-Dist: sphinxcontrib-autoprogram; extra == 'docs'
Provides-Extra: read_aligner_training
Requires-Dist: simplesam; extra == 'read_aligner_training'
Provides-Extra: tests
Requires-Dist: pytest (>=2.9); extra == 'tests'
